{
    "code":200,
    "status":"OK",
    "data":[
    {
    "number":1,
    "numberOfChannels":4,
    "channels":[
        {
            "titleChannel":"القائمة",
            "subTitleChannel":"Chekirou",
            "logoUrl":"https://raw.githubusercontent.com/cabdellah/C-A/main/tv/icon.png",
            "videoUrl":"https://cdn.islamic.network/quran/audio/128/ar.alafasy/1.mp3"
        },
        {
            "titleChannel":"المنزل",
            "subTitleChannel":"Chekirou",
            "logoUrl":"https://raw.githubusercontent.com/cabdellah/C-A/main/tv/icon.png",
            "videoUrl":"https://cdn.islamic.network/quran/audio/128/ar.alafasy/1.mp3"
        },
        {
            "titleChannel":"المشروع",
            "subTitleChannel":"Chekirou",
            "logoUrl":"https://raw.githubusercontent.com/cabdellah/C-A/main/tv/icon.png",
            "videoUrl":"https://cdn.islamic.network/quran/audio/128/ar.alafasy/1.mp3"
        },
        {
            "titleChannel":"الدار",
            "subTitleChannel":"Chekirou",
            "logoUrl":"https://raw.githubusercontent.com/cabdellah/C-A/main/tv/icon.png",
            "videoUrl":"https://cdn.islamic.network/quran/audio/128/ar.alafasy/1.mp3"
        }                
    ]
    },
    {
    "number":1,
    "name":"سُورَةُ ٱلْفَاتِحَةِ",
    "englishName":"Al-Faatiha",
    "englishNameTranslation":"The Opening",
    "revelationType":"Meccan",
    "numberOfChannels":7,
    "channels":[

    ],
    "edition":{
    "identifier":"en.asad",
    "language":"en",
    "name":"Asad",
    "englishName":"Muhammad Asad",
    "format":"text",
    "type":"translation",
    "direction":"ltr"
    }
    }
    ]
    }